protectedCalculator/__init__.py
protectedCalculator-0.3.dist-info/LICENSE.txt
protectedCalculator-0.3.dist-info/METADATA
protectedCalculator-0.3.dist-info/WHEEL
protectedCalculator-0.3.dist-info/top_level.txt
protectedCalculator-0.3.dist-info/RECORD
