Metadata-Version: 2.1
Name: protectedCalculator
Version: 0.3
Summary: calculator
Author: SARTHAK MEHROTRA
Author-email: i-sarthak@verdis.ai
Classifier: Programming Language :: Python :: 3
Classifier: License :: OSI Approved :: MIT License
Classifier: Operating System :: OS Independent
License-File: LICENSE.txt
